pypleo/__init__.py
pypleo/pleo_api_client.py
pypleo-2.0.1.dist-info/LICENSE
pypleo-2.0.1.dist-info/METADATA
pypleo-2.0.1.dist-info/WHEEL
pypleo-2.0.1.dist-info/top_level.txt
pypleo-2.0.1.dist-info/RECORD
